Metadata-Version: 1.0
Name: facebook-scribe-py3
Version: 0.1.1
Summary: A Python 3-compatible client for Facebook Scribe
Home-page: https://github.com/vears91/scribe-python/0.1
Author: Tom Primozic
Author-email: tom.primozic@zemanta.com
License: UNKNOWN
Platform: UNKNOWN
